cpp_operation.so
docs/source/conf.py
morphocore/__init__.py
morphocore/emorph.py
morphocore/functional/__init__.py
morphocore/functional/closing.py
morphocore/functional/dilation.py
morphocore/functional/emorph.py
morphocore/functional/erosion.py
morphocore/functional/merge_enum.py
morphocore/functional/opening.py
morphocore/functional/smorph.py
morphocore/nn/__init__.py
morphocore/nn/alpha_module.py
morphocore/nn/closing.py
morphocore/nn/dilation.py
morphocore/nn/emorph.py
morphocore/nn/erosion.py
morphocore/nn/morpho_module.py
morphocore/nn/opening.py
morphocore/nn/smorph.py
morphocore.libs/libcudart-c64a25f3.so.12.3.101
morphocore.libs/libgomp-870cb1d0.so.1.0.0
tests/__init__.py
tests/functional/__init__.py
tests/functional/conftest.py
tests/functional/test_cuda_cpu.py
tests/functional/test_indices_opti_cuda.py
tests/functional/test_morpho_operation.py
tests/functional/test_morpho_operation_speed.py
tests/functional/test_smorph.py
tests/functional/test_smorph_convergence.py
tests/functional/utils.py
morphocore-0.8.5.29.dist-info/METADATA
morphocore-0.8.5.29.dist-info/WHEEL
morphocore-0.8.5.29.dist-info/top_level.txt
morphocore-0.8.5.29.dist-info/RECORD
