Metadata-Version: 2.4
Name: morphocore
Version: 0.8.5.29
Summary: Morphological operations with CUDA acceleration
Author-email: Aurelien HURAND <aurelien.hurand@gmail.com>
License: MIT
Project-URL: Homepage, https://gitlab.lre.epita.fr/aurelien.hurand/morphocore
Project-URL: Bug Reports, https://gitlab.lre.epita.fr/aurelien.hurand/morphocore/-/issues
Project-URL: Source, https://gitlab.lre.epita.fr/aurelien.hurand/morphocore
Keywords: morphology,cuda,pytorch,computer-vision
Classifier: Development Status :: 3 - Alpha
Classifier: Intended Audience :: Developers
Classifier: Intended Audience :: Science/Research
Classifier: Programming Language :: Python :: 3
Classifier: Programming Language :: Python :: 3.10
Classifier: Programming Language :: Python :: 3.11
Classifier: Programming Language :: Python :: 3.12
Classifier: Programming Language :: C++
Classifier: Topic :: Scientific/Engineering
Classifier: Topic :: Scientific/Engineering :: Artificial Intelligence
Classifier: Topic :: Software Development :: Libraries :: Python Modules
Classifier: Topic :: Multimedia :: Graphics
Classifier: Environment :: GPU
Classifier: Environment :: GPU :: NVIDIA CUDA
Classifier: Operating System :: POSIX :: Linux
Requires-Python: >=3.10
Requires-Dist: torch<2.10.0,>=2.9.0
Requires-Dist: numpy>=1.19.0
Dynamic: requires-dist
